LICENSE.rst
MANIFEST.in
README
README.rst
setup.py
grimace/__init__.py
grimace/elements.py
grimace/extender.py
grimace/tests.py
grimace.egg-info/PKG-INFO
grimace.egg-info/SOURCES.txt
grimace.egg-info/dependency_links.txt
grimace.egg-info/not-zip-safe
grimace.egg-info/requires.txt
grimace.egg-info/top_level.txt